demos/__init__.py
demos/para_boot_for_normal_mean.py
functions/__init__.py
functions/dirichlet_logl.py
functions/gen_matrix.py
functions/linear_model_ols.py
functions/linearmodel.py
functions/load_data.py
functions/load_olympics.py
functions/load_weather.py
functions/soft_thresh.py
functions/vec_angle.py
functions/vec_norm.py
tests/__init__.py
tests/linearmodel_test.py
starlib-0.13.dist-info/LICENSE
starlib-0.13.dist-info/METADATA
starlib-0.13.dist-info/WHEEL
starlib-0.13.dist-info/top_level.txt
starlib-0.13.dist-info/RECORD
